quickbot_faststream/__init__.py
quickbot_faststream/config.py
quickbot_faststream/main.py
quickbot_faststream/utils.py
quickbot_faststream-0.1.0.dist-info/licenses/LICENSE
quickbot_faststream-0.1.0.dist-info/METADATA
quickbot_faststream-0.1.0.dist-info/WHEEL
quickbot_faststream-0.1.0.dist-info/top_level.txt
quickbot_faststream-0.1.0.dist-info/RECORD
